minsp/__init__.py
minsp/core.py
minsp/mo.py
minsp/pus.py
minsp/utils.py
minsp-0.0.3.dist-info/METADATA
minsp-0.0.3.dist-info/WHEEL
minsp-0.0.3.dist-info/licenses/LICENSE.txt
minsp-0.0.3.dist-info/RECORD
