Metadata-Version: 2.4
Name: minsp
Version: 0.0.3
Summary: minimalistic implementation of the Space Packet specification from the CCSDS Space Packet Protocol standard
Author-email: Nuno Carvalho <narcarvalho@gmail.com>
License-File: LICENSE.txt
Requires-Python: ~=3.10
